{
  "main": {
    "id": "fe33dbe6ec876a32",
    "type": "split",
    "children": [
      {
        "id": "b46df044c14fcde8",
        "type": "tabs",
        "children": [
          {
            "id": "9eb0103fd74e91b3",
            "type": "leaf",
            "state": {
              "type": "markdown",
              "state": {
                "file": "Дизайн-документ. Supermarket Empire Simulator.md",
                "mode": "source",
                "source": false
              },
              "icon": "lucide-file",
              "title": "Дизайн-документ. Supermarket Empire Simulator"
            }
          },
          {
            "id": "f672da779709ebac",
            "type": "leaf",
            "state": {
              "type": "markdown",
              "state": {
                "file": "ИИ Покупателей.md",
                "mode": "source",
                "source": false
              },
              "icon": "lucide-file",
              "title": "ИИ Покупателей"
            }
          }
        ],
        "currentTab": 1
      }
    ],
    "direction": "vertical"
  },
  "left": {
    "id": "b409340843993559",
    "type": "split",
    "children": [
      {
        "id": "8fc6ca65d58a7a72",
        "type": "tabs",
        "children": [
          {
            "id": "0e788fb2574eb9d8",
            "type": "leaf",
            "state": {
              "type": "file-explorer",
              "state": {
                "sortOrder": "alphabetical",
                "autoReveal": false
              },
              "icon": "lucide-folder-closed",
              "title": "Files"
            }
          },
          {
            "id": "164055f03820840a",
            "type": "leaf",
            "state": {
              "type": "search",
              "state": {
                "query": "",
                "matchingCase": false,
                "explainSearch": false,
                "collapseAll": false,
                "extraContext": false,
                "sortOrder": "alphabetical"
              },
              "icon": "lucide-search",
              "title": "Search"
            }
          },
          {
            "id": "4d24e454b9abf465",
            "type": "leaf",
            "state": {
              "type": "bookmarks",
              "state": {},
              "icon": "lucide-bookmark",
              "title": "Bookmarks"
            }
          }
        ]
      }
    ],
    "direction": "horizontal",
    "width": 300
  },
  "right": {
    "id": "6a1e5ca57a5030af",
    "type": "split",
    "children": [
      {
        "id": "7ea988163b2f3a33",
        "type": "tabs",
        "children": [
          {
            "id": "037ca6fbf40ff0c4",
            "type": "leaf",
            "state": {
              "type": "backlink",
              "state": {
                "file": "ИИ Покупателей.md",
                "collapseAll": false,
                "extraContext": false,
                "sortOrder": "alphabetical",
                "showSearch": false,
                "searchQuery": "",
                "backlinkCollapsed": false,
                "unlinkedCollapsed": true
              },
              "icon": "links-coming-in",
              "title": "Backlinks for ИИ Покупателей"
            }
          },
          {
            "id": "1299455c71a13d89",
            "type": "leaf",
            "state": {
              "type": "outgoing-link",
              "state": {
                "file": "ИИ Покупателей.md",
                "linksCollapsed": false,
                "unlinkedCollapsed": true
              },
              "icon": "links-going-out",
              "title": "Outgoing links from ИИ Покупателей"
            }
          },
          {
            "id": "868227cd0148c8cb",
            "type": "leaf",
            "state": {
              "type": "tag",
              "state": {
                "sortOrder": "frequency",
                "useHierarchy": true,
                "showSearch": false,
                "searchQuery": ""
              },
              "icon": "lucide-tags",
              "title": "Tags"
            }
          },
          {
            "id": "2c8cf4c22675e481",
            "type": "leaf",
            "state": {
              "type": "outline",
              "state": {
                "file": "ИИ Покупателей.md",
                "followCursor": false,
                "showSearch": false,
                "searchQuery": ""
              },
              "icon": "lucide-list",
              "title": "Outline of ИИ Покупателей"
            }
          }
        ]
      }
    ],
    "direction": "horizontal",
    "width": 300,
    "collapsed": true
  },
  "left-ribbon": {
    "hiddenItems": {
      "switcher:Open quick switcher": false,
      "graph:Open graph view": false,
      "canvas:Create new canvas": false,
      "daily-notes:Open today's daily note": false,
      "templates:Insert template": false,
      "command-palette:Open command palette": false
    }
  },
  "active": "f672da779709ebac",
  "lastOpenFiles": [
    "Дизайн-документ. Supermarket Empire Simulator.md",
    "ИИ Покупателей.md",
    "Welcome.md"
  ]
}